textme_mcp/__init__.py
textme_mcp/server.py
textme_mcp-0.1.1.dist-info/METADATA
textme_mcp-0.1.1.dist-info/WHEEL
textme_mcp-0.1.1.dist-info/entry_points.txt
textme_mcp-0.1.1.dist-info/top_level.txt
textme_mcp-0.1.1.dist-info/RECORD
