Metadata-Version: 2.4
Name: textme-mcp
Version: 0.1.1
Summary: 大模型调用textme的服务发送推送消息
Requires-Python: >=3.13
Requires-Dist: dotenv>=0.9.9
Requires-Dist: httpx>=0.28.1
Requires-Dist: mcp[cli]>=1.10.1
